{
  "__inputs": [
    {
      "name": "DS_PROMETHEUS",
      "label": "prometheus",
      "description": "",
      "type": "datasource",
      "pluginId": "prometheus",
      "pluginName": "Prometheus"
    }
  ],
  "__requires": [
    {
      "type": "grafana",
      "id": "grafana",
      "name": "Grafana",
      "version": "7.3.3"
    },
    {
      "type": "panel",
      "id": "graph",
      "name": "Graph",
      "version": ""
    },
    {
      "type": "datasource",
      "id": "prometheus",
      "name": "Prometheus",
      "version": "1.0.0"
    },
    {
      "type": "panel",
      "id": "singlestat",
      "name": "Singlestat",
      "version": ""
    }
  ],
  "annotations": {
    "list": [
      {
        "builtIn": 1,
        "datasource": "-- Grafana --",
        "enable": true,
        "hide": true,
        "iconColor": "rgba(0, 211, 255, 1)",
        "name": "Annotations & Alerts",
        "type": "dashboard"
      }
    ]
  },
  "editable": true,
  "gnetId": null,
  "graphTooltip": 0,
  "id": null,
  "iteration": 1631898340845,
  "links": [
    {
      "asDropdown": true,
      "icon": "external link",
      "includeVars": true,
      "keepTime": true,
      "tags": [
        "cf"
      ],
      "targetBlank": false,
      "title": "CF",
      "type": "dashboards"
    },
    {
      "asDropdown": true,
      "icon": "external link",
      "includeVars": true,
      "keepTime": true,
      "tags": [
        "v2"
      ],
      "targetBlank": true,
      "title": "v2 Dashboards",
      "type": "dashboards"
    },
    {
      "icon": "external link",
      "tags": [],
      "targetBlank": true,
      "title": "CF Component Metrics",
      "type": "link",
      "url": "https://docs.cloudfoundry.org/loggregator/all_metrics.html"
    }
  ],
  "panels": [
    {
      "cacheTimeout": null,
      "colorBackground": false,
      "colorValue": true,
      "colors": [
        "rgba(50, 172, 45, 0.97)",
        "rgba(237, 129, 40, 0.89)",
        "rgba(245, 54, 54, 0.9)"
      ],
      "datasource": "${DS_PROMETHEUS}",
      "description": "Whether the cell has failed to pass its healthcheck against the garden backend.",
      "fieldConfig": {
        "defaults": {
          "custom": {}
        },
        "overrides": []
      },
      "format": "none",
      "gauge": {
        "maxValue": 100,
        "minValue": 0,
        "show": false,
        "thresholdLabels": false,
        "thresholdMarkers": true
      },
      "gridPos": {
        "h": 4,
        "w": 3,
        "x": 0,
        "y": 0
      },
      "id": 24,
      "interval": null,
      "links": [],
      "mappingType": 1,
      "mappingTypes": [
        {
          "$$hashKey": "object:245",
          "name": "value to text",
          "value": 1
        },
        {
          "$$hashKey": "object:246",
          "name": "range to text",
          "value": 2
        }
      ],
      "maxDataPoints": 100,
      "nullPointMode": "connected",
      "nullText": null,
      "postfix": "",
      "postfixFontSize": "50%",
      "prefix": "",
      "prefixFontSize": "50%",
      "rangeMaps": [
        {
          "from": "null",
          "text": "N/A",
          "to": "null"
        }
      ],
      "sparkline": {
        "fillColor": "rgba(31, 118, 189, 0.18)",
        "full": false,
        "lineColor": "rgb(31, 120, 193)",
        "show": true
      },
      "tableColumn": "",
      "targets": [
        {
          "expr": "count(min(firehose_value_metric_rep_garden_health_check_failed{environment=~\"$environment\",bosh_deployment=~\"${bosh_deployment}[-0-9a-f]*\"}) by(bosh_deployment, bosh_job_name, bosh_job_ip) == 1)",
          "interval": "",
          "intervalFactor": 2,
          "legendFormat": "",
          "refId": "A",
          "step": 60
        }
      ],
      "thresholds": "0,5",
      "title": "Unhealthy Cells",
      "transparent": true,
      "type": "singlestat",
      "valueFontSize": "80%",
      "valueMaps": [
        {
          "$$hashKey": "object:248",
          "op": "=",
          "text": "0",
          "value": "null"
        }
      ],
      "valueName": "current"
    },
    {
      "cacheTimeout": null,
      "colorBackground": false,
      "colorValue": true,
      "colors": [
        "rgba(50, 172, 45, 0.97)",
        "rgba(237, 129, 40, 0.89)",
        "rgba(245, 54, 54, 0.9)"
      ],
      "datasource": "${DS_PROMETHEUS}",
      "fieldConfig": {
        "defaults": {
          "custom": {}
        },
        "overrides": []
      },
      "format": "none",
      "gauge": {
        "maxValue": 100,
        "minValue": 0,
        "show": false,
        "thresholdLabels": false,
        "thresholdMarkers": true
      },
      "gridPos": {
        "h": 4,
        "w": 3,
        "x": 3,
        "y": 0
      },
      "id": 7,
      "interval": null,
      "links": [],
      "mappingType": 1,
      "mappingTypes": [
        {
          "$$hashKey": "object:286",
          "name": "value to text",
          "value": 1
        },
        {
          "$$hashKey": "object:287",
          "name": "range to text",
          "value": 2
        }
      ],
      "maxDataPoints": 100,
      "nullPointMode": "connected",
      "nullText": null,
      "postfix": "",
      "postfixFontSize": "50%",
      "prefix": "",
      "prefixFontSize": "50%",
      "rangeMaps": [
        {
          "from": "null",
          "text": "N/A",
          "to": "null"
        }
      ],
      "sparkline": {
        "fillColor": "rgba(31, 118, 189, 0.18)",
        "full": false,
        "lineColor": "rgb(31, 120, 193)",
        "show": false
      },
      "tableColumn": "",
      "targets": [
        {
          "expr": "max(firehose_value_metric_bbs_lr_ps_missing{environment=~\"$environment\",bosh_deployment=~\"${bosh_deployment}[-0-9a-f]*\"})",
          "interval": "",
          "intervalFactor": 2,
          "legendFormat": "",
          "metric": "firehose_value_metric_bbs_lr_ps_missing",
          "refId": "A",
          "step": 60
        },
        {
          "expr": "lr_p",
          "interval": "",
          "legendFormat": "",
          "refId": "B"
        }
      ],
      "thresholds": "5,10",
      "title": "LRPs Missing",
      "transparent": true,
      "type": "singlestat",
      "valueFontSize": "80%",
      "valueMaps": [
        {
          "$$hashKey": "object:289",
          "op": "=",
          "text": "N/A",
          "value": "null"
        }
      ],
      "valueName": "avg"
    },
    {
      "cacheTimeout": null,
      "colorBackground": false,
      "colorValue": true,
      "colors": [
        "rgba(245, 54, 54, 0.9)",
        "rgba(237, 129, 40, 0.89)",
        "rgba(50, 172, 45, 0.97)"
      ],
      "datasource": "${DS_PROMETHEUS}",
      "description": "Whether the cf-app domain is up-to-date, so that CF apps from CC have been synchronized with DesiredLRPs for Diego to run.",
      "fieldConfig": {
        "defaults": {
          "custom": {}
        },
        "overrides": []
      },
      "format": "none",
      "gauge": {
        "maxValue": 100,
        "minValue": 0,
        "show": false,
        "thresholdLabels": false,
        "thresholdMarkers": true
      },
      "gridPos": {
        "h": 4,
        "w": 3,
        "x": 6,
        "y": 0
      },
      "id": 5,
      "interval": null,
      "links": [],
      "mappingType": 1,
      "mappingTypes": [
        {
          "$$hashKey": "object:327",
          "name": "value to text",
          "value": 1
        },
        {
          "$$hashKey": "object:328",
          "name": "range to text",
          "value": 2
        }
      ],
      "maxDataPoints": 100,
      "nullPointMode": "connected",
      "nullText": null,
      "postfix": "",
      "postfixFontSize": "50%",
      "prefix": "",
      "prefixFontSize": "50%",
      "rangeMaps": [
        {
          "from": "null",
          "text": "N/A",
          "to": "null"
        }
      ],
      "sparkline": {
        "fillColor": "rgba(31, 118, 189, 0.18)",
        "full": false,
        "lineColor": "rgb(2, 85, 225)",
        "show": false
      },
      "tableColumn": "",
      "targets": [
        {
          "expr": "min(firehose_value_metric_bbs_domain_cf_apps{environment=~\"$environment\",bosh_deployment=~\"${bosh_deployment}[-0-9a-f]*\"})",
          "hide": false,
          "interval": "",
          "intervalFactor": 2,
          "legendFormat": "",
          "metric": "firehose_value_metric_bbs_domain_cf_apps",
          "refId": "A",
          "step": 60
        }
      ],
      "thresholds": "0.9,1",
      "title": "CF Apps Synchronized",
      "transparent": true,
      "type": "singlestat",
      "valueFontSize": "80%",
      "valueMaps": [
        {
          "$$hashKey": "object:330",
          "op": "=",
          "text": "N/A",
          "value": "null"
        },
        {
          "$$hashKey": "object:331",
          "op": "=",
          "text": "NOK",
          "value": "0"
        },
        {
          "$$hashKey": "object:332",
          "op": "=",
          "text": "OK",
          "value": "1"
        }
      ],
      "valueName": "current"
    },
    {
      "cacheTimeout": null,
      "colorBackground": false,
      "colorValue": true,
      "colors": [
        "rgba(245, 54, 54, 0.9)",
        "rgba(237, 129, 40, 0.89)",
        "rgba(50, 172, 45, 0.97)"
      ],
      "datasource": "${DS_PROMETHEUS}",
      "description": "Whether the cf-tasks domain is up-to-date, so that CF tasks from CC have been synchronized with tasks for Diego to run.",
      "fieldConfig": {
        "defaults": {
          "custom": {}
        },
        "overrides": []
      },
      "format": "none",
      "gauge": {
        "maxValue": 100,
        "minValue": 0,
        "show": false,
        "thresholdLabels": false,
        "thresholdMarkers": true
      },
      "gridPos": {
        "h": 4,
        "w": 3,
        "x": 9,
        "y": 0
      },
      "id": 23,
      "interval": null,
      "links": [],
      "mappingType": 1,
      "mappingTypes": [
        {
          "$$hashKey": "object:372",
          "name": "value to text",
          "value": 1
        },
        {
          "$$hashKey": "object:373",
          "name": "range to text",
          "value": 2
        }
      ],
      "maxDataPoints": 100,
      "nullPointMode": "connected",
      "nullText": null,
      "postfix": "",
      "postfixFontSize": "50%",
      "prefix": "",
      "prefixFontSize": "50%",
      "rangeMaps": [
        {
          "from": "null",
          "text": "N/A",
          "to": "null"
        }
      ],
      "sparkline": {
        "fillColor": "rgba(31, 118, 189, 0.18)",
        "full": false,
        "lineColor": "rgb(2, 85, 225)",
        "show": false
      },
      "tableColumn": "",
      "targets": [
        {
          "expr": "min(firehose_value_metric_bbs_domain_cf_tasks{environment=~\"$environment\",bosh_deployment=~\"${bosh_deployment}[-0-9a-f]*\"})",
          "hide": false,
          "interval": "",
          "intervalFactor": 2,
          "legendFormat": "",
          "metric": "firehose_value_metric_bbs_domain_cf_apps",
          "refId": "A",
          "step": 60
        }
      ],
      "thresholds": "0.9,1",
      "title": "CF Tasks Synchronized",
      "transparent": true,
      "type": "singlestat",
      "valueFontSize": "80%",
      "valueMaps": [
        {
          "$$hashKey": "object:375",
          "op": "=",
          "text": "N/A",
          "value": "null"
        },
        {
          "$$hashKey": "object:376",
          "op": "=",
          "text": "NOK",
          "value": "0"
        },
        {
          "$$hashKey": "object:377",
          "op": "=",
          "text": "OK",
          "value": "1"
        }
      ],
      "valueName": "current"
    },
    {
      "cacheTimeout": null,
      "colorBackground": false,
      "colorValue": true,
      "colors": [
        "rgba(50, 172, 45, 0.97)",
        "rgba(237, 129, 40, 0.89)",
        "rgba(245, 54, 54, 0.9)"
      ],
      "datasource": "${DS_PROMETHEUS}",
      "fieldConfig": {
        "defaults": {
          "custom": {}
        },
        "overrides": []
      },
      "format": "none",
      "gauge": {
        "maxValue": 100,
        "minValue": 0,
        "show": false,
        "thresholdLabels": false,
        "thresholdMarkers": true
      },
      "gridPos": {
        "h": 4,
        "w": 3,
        "x": 12,
        "y": 0
      },
      "id": 32,
      "interval": null,
      "links": [],
      "mappingType": 1,
      "mappingTypes": [
        {
          "$$hashKey": "object:417",
          "name": "value to text",
          "value": 1
        },
        {
          "$$hashKey": "object:418",
          "name": "range to text",
          "value": 2
        }
      ],
      "maxDataPoints": 100,
      "nullPointMode": "connected",
      "nullText": null,
      "postfix": "",
      "postfixFontSize": "50%",
      "prefix": "",
      "prefixFontSize": "50%",
      "rangeMaps": [
        {
          "from": "null",
          "text": "N/A",
          "to": "null"
        }
      ],
      "sparkline": {
        "fillColor": "rgba(31, 118, 189, 0.18)",
        "full": false,
        "lineColor": "rgb(31, 120, 193)",
        "show": false
      },
      "tableColumn": "",
      "targets": [
        {
          "expr": "max(firehose_slow_consumer_alert{environment=~\"$environment\"})",
          "interval": "",
          "intervalFactor": 2,
          "legendFormat": "",
          "refId": "A",
          "step": 60
        }
      ],
      "thresholds": "0.9,1",
      "title": "Slow Consumer Alert",
      "transparent": true,
      "type": "singlestat",
      "valueFontSize": "80%",
      "valueMaps": [
        {
          "$$hashKey": "object:420",
          "op": "=",
          "text": "N/A",
          "value": "null"
        },
        {
          "$$hashKey": "object:421",
          "op": "=",
          "text": "OK",
          "value": "0"
        },
        {
          "$$hashKey": "object:422",
          "op": "=",
          "text": "NOK",
          "value": "1"
        }
      ],
      "valueName": "current"
    },
    {
      "cacheTimeout": null,
      "colorBackground": false,
      "colorValue": false,
      "colors": [
        "rgba(50, 172, 45, 0.97)",
        "rgba(237, 129, 40, 0.89)",
        "rgba(245, 54, 54, 0.9)"
      ],
      "datasource": "${DS_PROMETHEUS}",
      "fieldConfig": {
        "defaults": {
          "custom": {}
        },
        "overrides": []
      },
      "format": "none",
      "gauge": {
        "maxValue": 50,
        "minValue": 0,
        "show": false,
        "thresholdLabels": false,
        "thresholdMarkers": true
      },
      "gridPos": {
        "h": 4,
        "w": 4,
        "x": 16,
        "y": 0
      },
      "id": 8,
      "interval": null,
      "links": [],
      "mappingType": 1,
      "mappingTypes": [
        {
          "$$hashKey": "object:465",
          "name": "value to text",
          "value": 1
        },
        {
          "$$hashKey": "object:466",
          "name": "range to text",
          "value": 2
        }
      ],
      "maxDataPoints": 100,
      "nullPointMode": "connected",
      "nullText": null,
      "postfix": "",
      "postfixFontSize": "50%",
      "prefix": "",
      "prefixFontSize": "50%",
      "rangeMaps": [
        {
          "from": "null",
          "text": "N/A",
          "to": "null"
        }
      ],
      "sparkline": {
        "fillColor": "rgba(31, 118, 189, 0.18)",
        "full": false,
        "lineColor": "rgb(31, 120, 193)",
        "show": true
      },
      "tableColumn": "",
      "targets": [
        {
          "expr": "avg(avg_over_time(firehose_value_metric_bbs_lr_ps_running{environment=~\"$environment\",bosh_deployment=~\"${bosh_deployment}[-0-9a-f]*\"}[1d]))",
          "interval": "",
          "intervalFactor": 2,
          "legendFormat": "",
          "metric": "firehose_value_metric_bbs_lr_ps_running",
          "refId": "A",
          "step": 60
        }
      ],
      "thresholds": "",
      "title": "Avg LRPs 24h",
      "transparent": true,
      "type": "singlestat",
      "valueFontSize": "80%",
      "valueMaps": [
        {
          "$$hashKey": "object:468",
          "op": "=",
          "text": "N/A",
          "value": "null"
        }
      ],
      "valueName": "avg"
    },
    {
      "cacheTimeout": null,
      "colorBackground": false,
      "colorValue": false,
      "colors": [
        "rgba(245, 54, 54, 0.9)",
        "rgba(237, 129, 40, 0.89)",
        "rgba(50, 172, 45, 0.97)"
      ],
      "datasource": "${DS_PROMETHEUS}",
      "description": "Number of routes registered.",
      "fieldConfig": {
        "defaults": {
          "custom": {}
        },
        "overrides": []
      },
      "format": "none",
      "gauge": {
        "maxValue": 100,
        "minValue": 0,
        "show": false,
        "thresholdLabels": false,
        "thresholdMarkers": true
      },
      "gridPos": {
        "h": 4,
        "w": 4,
        "x": 20,
        "y": 0
      },
      "id": 14,
      "interval": null,
      "links": [],
      "mappingType": 1,
      "mappingTypes": [
        {
          "$$hashKey": "object:590",
          "name": "value to text",
          "value": 1
        },
        {
          "$$hashKey": "object:591",
          "name": "range to text",
          "value": 2
        }
      ],
      "maxDataPoints": 100,
      "nullPointMode": "connected",
      "nullText": null,
      "postfix": "",
      "postfixFontSize": "50%",
      "prefix": "",
      "prefixFontSize": "50%",
      "rangeMaps": [
        {
          "from": "null",
          "text": "N/A",
          "to": "null"
        }
      ],
      "sparkline": {
        "fillColor": "rgba(31, 118, 189, 0.18)",
        "full": false,
        "lineColor": "rgb(31, 120, 193)",
        "show": true
      },
      "tableColumn": "Routes",
      "targets": [
        {
          "expr": "avg(firehose_value_metric_gorouter_total_routes{environment=~\"$environment\",bosh_deployment=~\"${bosh_deployment}[-0-9a-f]*\"})",
          "interval": "",
          "intervalFactor": 2,
          "legendFormat": "Routes",
          "metric": "firehose_value_metric_gorouter_total_routes",
          "refId": "A",
          "step": 60
        }
      ],
      "thresholds": "",
      "title": "Routes",
      "transparent": true,
      "type": "singlestat",
      "valueFontSize": "80%",
      "valueMaps": [
        {
          "$$hashKey": "object:593",
          "op": "=",
          "text": "N/A",
          "value": "null"
        }
      ],
      "valueName": "avg"
    },
    {
      "aliasColors": {},
      "bars": false,
      "dashLength": 10,
      "dashes": false,
      "datasource": "${DS_PROMETHEUS}",
      "description": "Available MiB of memory to allocate to containers.",
      "fieldConfig": {
        "defaults": {
          "custom": {}
        },
        "overrides": []
      },
      "fill": 1,
      "fillGradient": 0,
      "gridPos": {
        "h": 5,
        "w": 8,
        "x": 0,
        "y": 4
      },
      "hiddenSeries": false,
      "id": 10,
      "legend": {
        "alignAsTable": false,
        "avg": false,
        "current": false,
        "max": false,
        "min": false,
        "rightSide": false,
        "show": true,
        "total": false,
        "values": false
      },
      "lines": true,
      "linewidth": 1,
      "links": [],
      "nullPointMode": "null",
      "options": {
        "alertThreshold": true
      },
      "percentage": false,
      "pluginVersion": "7.3.3",
      "pointradius": 5,
      "points": false,
      "renderer": "flot",
      "seriesOverrides": [
        {
          "$$hashKey": "object:653",
          "alias": "Total available memory",
          "yaxis": 1
        }
      ],
      "spaceLength": 10,
      "stack": false,
      "steppedLine": false,
      "targets": [
        {
          "expr": "min(avg(firehose_value_metric_rep_capacity_remaining_memory{environment=~\"$environment\",bosh_deployment=~\"${bosh_deployment}[-0-9a-f]*\"}) by(bosh_deployment, bosh_job_name, bosh_job_ip))",
          "interval": "",
          "intervalFactor": 2,
          "legendFormat": "Cell with Least Available Memory",
          "metric": "firehose_value_metric_rep_capacity_remaining_memory",
          "refId": "A",
          "step": 10
        },
        {
          "expr": "max(avg(firehose_value_metric_rep_capacity_remaining_memory{environment=~\"$environment\",bosh_deployment=~\"${bosh_deployment}[-0-9a-f]*\"}) by(bosh_deployment, bosh_job_name, bosh_job_ip))",
          "interval": "",
          "intervalFactor": 2,
          "legendFormat": "Cell with Most Available Memory",
          "metric": "",
          "refId": "B",
          "step": 10
        },
        {
          "expr": "sum(avg(firehose_value_metric_rep_capacity_remaining_memory{environment=~\"$environment\",bosh_deployment=~\"${bosh_deployment}[-0-9a-f]*\"}) by(bosh_deployment, bosh_job_name, bosh_job_ip))",
          "interval": "",
          "intervalFactor": 2,
          "legendFormat": "Total Available Available Memory",
          "refId": "C",
          "step": 10
        }
      ],
      "thresholds": [],
      "timeFrom": null,
      "timeRegions": [],
      "timeShift": null,
      "title": "Available Memory",
      "tooltip": {
        "shared": true,
        "sort": 0,
        "value_type": "individual"
      },
      "transparent": true,
      "type": "graph",
      "xaxis": {
        "buckets": null,
        "mode": "time",
        "name": null,
        "show": true,
        "values": []
      },
      "yaxes": [
        {
          "$$hashKey": "object:660",
          "format": "mbytes",
          "label": null,
          "logBase": 1,
          "max": null,
          "min": "0",
          "show": true
        },
        {
          "$$hashKey": "object:661",
          "format": "mbytes",
          "label": null,
          "logBase": 1,
          "max": null,
          "min": null,
          "show": false
        }
      ],
      "yaxis": {
        "align": false,
        "alignLevel": null
      }
    },
    {
      "aliasColors": {},
      "bars": false,
      "dashLength": 10,
      "dashes": false,
      "datasource": "${DS_PROMETHEUS}",
      "description": "Available MiB of disk to allocate to containers.",
      "fieldConfig": {
        "defaults": {
          "custom": {}
        },
        "overrides": []
      },
      "fill": 1,
      "fillGradient": 0,
      "gridPos": {
        "h": 5,
        "w": 8,
        "x": 8,
        "y": 4
      },
      "hiddenSeries": false,
      "id": 12,
      "legend": {
        "alignAsTable": false,
        "avg": false,
        "current": false,
        "max": false,
        "min": false,
        "rightSide": false,
        "show": true,
        "total": false,
        "values": false
      },
      "lines": true,
      "linewidth": 1,
      "links": [],
      "nullPointMode": "null",
      "options": {
        "alertThreshold": true
      },
      "percentage": false,
      "pluginVersion": "7.3.3",
      "pointradius": 5,
      "points": false,
      "renderer": "flot",
      "seriesOverrides": [],
      "spaceLength": 10,
      "stack": false,
      "steppedLine": false,
      "targets": [
        {
          "expr": "min(avg(firehose_value_metric_rep_capacity_remaining_disk{environment=~\"$environment\",bosh_deployment=~\"${bosh_deployment}[-0-9a-f]*\"}) by(bosh_deployment, bosh_job_name, bosh_job_ip))",
          "interval": "",
          "intervalFactor": 2,
          "legendFormat": "Cell with Least Available Disk",
          "metric": "firehose_value_metric_rep_capacity_remaining_memory",
          "refId": "A",
          "step": 10
        },
        {
          "expr": "max(avg(firehose_value_metric_rep_capacity_remaining_disk{environment=~\"$environment\",bosh_deployment=~\"${bosh_deployment}[-0-9a-f]*\"}) by(bosh_deployment, bosh_job_name, bosh_job_ip))",
          "interval": "",
          "intervalFactor": 2,
          "legendFormat": "Cell with Most Available Disk",
          "metric": "",
          "refId": "B",
          "step": 10
        },
        {
          "expr": "sum(avg(firehose_value_metric_rep_capacity_remaining_disk{environment=~\"$environment\",bosh_deployment=~\"${bosh_deployment}[-0-9a-f]*\"}) by(bosh_deployment, bosh_job_name, bosh_job_ip))",
          "interval": "",
          "intervalFactor": 2,
          "legendFormat": "Total Available Disk",
          "refId": "C",
          "step": 10
        }
      ],
      "thresholds": [],
      "timeFrom": null,
      "timeRegions": [],
      "timeShift": null,
      "title": "Available Disk",
      "tooltip": {
        "shared": true,
        "sort": 0,
        "value_type": "individual"
      },
      "transparent": true,
      "type": "graph",
      "xaxis": {
        "buckets": null,
        "mode": "time",
        "name": null,
        "show": true,
        "values": []
      },
      "yaxes": [
        {
          "$$hashKey": "object:742",
          "format": "mbytes",
          "label": null,
          "logBase": 1,
          "max": null,
          "min": "0",
          "show": true
        },
        {
          "$$hashKey": "object:743",
          "format": "mbytes",
          "label": null,
          "logBase": 1,
          "max": null,
          "min": null,
          "show": false
        }
      ],
      "yaxis": {
        "align": false,
        "alignLevel": null
      }
    },
    {
      "aliasColors": {},
      "bars": false,
      "dashLength": 10,
      "dashes": false,
      "datasource": "${DS_PROMETHEUS}",
      "description": "Available number of containers.",
      "fieldConfig": {
        "defaults": {
          "custom": {}
        },
        "overrides": []
      },
      "fill": 1,
      "fillGradient": 0,
      "gridPos": {
        "h": 5,
        "w": 8,
        "x": 16,
        "y": 4
      },
      "hiddenSeries": false,
      "id": 19,
      "legend": {
        "alignAsTable": false,
        "avg": false,
        "current": false,
        "max": false,
        "min": false,
        "rightSide": false,
        "show": true,
        "total": false,
        "values": false
      },
      "lines": true,
      "linewidth": 1,
      "links": [],
      "nullPointMode": "null",
      "options": {
        "alertThreshold": true
      },
      "percentage": false,
      "pluginVersion": "7.3.3",
      "pointradius": 5,
      "points": false,
      "renderer": "flot",
      "seriesOverrides": [],
      "spaceLength": 10,
      "stack": false,
      "steppedLine": false,
      "targets": [
        {
          "expr": "min(avg(firehose_value_metric_rep_capacity_remaining_containers{environment=~\"$environment\",bosh_deployment=~\"${bosh_deployment}\"}) by(bosh_deployment, bosh_job_name, bosh_job_ip))",
          "interval": "",
          "intervalFactor": 2,
          "legendFormat": "Cell with Least Available Containers",
          "metric": "firehose_value_metric_rep_capacity_remaining_memory",
          "refId": "A",
          "step": 10
        },
        {
          "expr": "max(avg(firehose_value_metric_rep_capacity_remaining_containers{environment=~\"$environment\",bosh_deployment=~\"${bosh_deployment}\"}) by(bosh_deployment, bosh_job_name, bosh_job_ip))",
          "interval": "",
          "intervalFactor": 2,
          "legendFormat": "Cell with Most Available Containers",
          "metric": "",
          "refId": "B",
          "step": 10
        },
        {
          "expr": "sum(avg(firehose_value_metric_rep_capacity_remaining_containers{environment=~\"$environment\",bosh_deployment=~\"${bosh_deployment}\"}) by(bosh_deployment, bosh_job_name, bosh_job_ip))",
          "interval": "",
          "intervalFactor": 2,
          "legendFormat": "Total Available Containers",
          "refId": "C",
          "step": 10
        }
      ],
      "thresholds": [],
      "timeFrom": null,
      "timeRegions": [],
      "timeShift": null,
      "title": "Available Containers",
      "tooltip": {
        "shared": true,
        "sort": 0,
        "value_type": "individual"
      },
      "transparent": true,
      "type": "graph",
      "xaxis": {
        "buckets": null,
        "mode": "time",
        "name": null,
        "show": true,
        "values": []
      },
      "yaxes": [
        {
          "$$hashKey": "object:823",
          "format": "none",
          "label": null,
          "logBase": 1,
          "max": null,
          "min": "0",
          "show": true
        },
        {
          "$$hashKey": "object:824",
          "format": "mbytes",
          "label": null,
          "logBase": 1,
          "max": null,
          "min": null,
          "show": false
        }
      ],
      "yaxis": {
        "align": false,
        "alignLevel": null
      }
    },
    {
      "aliasColors": {},
      "bars": false,
      "dashLength": 10,
      "dashes": false,
      "datasource": "${DS_PROMETHEUS}",
      "description": "Max number of requests per second received by the BBS.",
      "fieldConfig": {
        "defaults": {
          "custom": {}
        },
        "overrides": []
      },
      "fill": 1,
      "fillGradient": 0,
      "gridPos": {
        "h": 5,
        "w": 8,
        "x": 0,
        "y": 9
      },
      "hiddenSeries": false,
      "id": 20,
      "legend": {
        "avg": false,
        "current": false,
        "max": false,
        "min": false,
        "show": false,
        "total": false,
        "values": false
      },
      "lines": true,
      "linewidth": 1,
      "links": [],
      "nullPointMode": "null",
      "options": {
        "alertThreshold": true
      },
      "percentage": false,
      "pluginVersion": "7.3.3",
      "pointradius": 5,
      "points": false,
      "renderer": "flot",
      "seriesOverrides": [],
      "spaceLength": 10,
      "stack": false,
      "steppedLine": false,
      "targets": [
        {
          "expr": "max(rate(firehose_counter_event_bbs_request_count_total{environment=~\"$environment\",bosh_deployment=~\"${bosh_deployment}[-0-9a-f]*\"}[5m]))",
          "interval": "",
          "intervalFactor": 2,
          "legendFormat": "Req/Sec",
          "refId": "A",
          "step": 10
        }
      ],
      "thresholds": [],
      "timeFrom": null,
      "timeRegions": [],
      "timeShift": null,
      "title": "BBS Requests per Second (max)",
      "tooltip": {
        "shared": true,
        "sort": 0,
        "value_type": "individual"
      },
      "transparent": true,
      "type": "graph",
      "xaxis": {
        "buckets": null,
        "mode": "time",
        "name": null,
        "show": true,
        "values": []
      },
      "yaxes": [
        {
          "$$hashKey": "object:904",
          "format": "short",
          "label": null,
          "logBase": 1,
          "max": null,
          "min": "0",
          "show": true
        },
        {
          "$$hashKey": "object:905",
          "format": "short",
          "label": null,
          "logBase": 1,
          "max": null,
          "min": null,
          "show": false
        }
      ],
      "yaxis": {
        "align": false,
        "alignLevel": null
      }
    },
    {
      "aliasColors": {},
      "bars": false,
      "dashLength": 10,
      "dashes": false,
      "datasource": "${DS_PROMETHEUS}",
      "description": "Max time in nanoseconds that the BBS took to handle requests to its API endpoints.",
      "fieldConfig": {
        "defaults": {
          "custom": {}
        },
        "overrides": []
      },
      "fill": 1,
      "fillGradient": 0,
      "gridPos": {
        "h": 5,
        "w": 8,
        "x": 8,
        "y": 9
      },
      "hiddenSeries": false,
      "id": 6,
      "legend": {
        "alignAsTable": false,
        "avg": false,
        "current": false,
        "max": false,
        "min": false,
        "show": false,
        "total": false,
        "values": false
      },
      "lines": true,
      "linewidth": 1,
      "links": [],
      "nullPointMode": "null",
      "options": {
        "alertThreshold": true
      },
      "percentage": false,
      "pluginVersion": "7.3.3",
      "pointradius": 5,
      "points": false,
      "renderer": "flot",
      "seriesOverrides": [],
      "spaceLength": 10,
      "stack": false,
      "steppedLine": false,
      "targets": [
        {
          "expr": "max(firehose_value_metric_bbs_request_latency{environment=~\"$environment\",bosh_deployment=~\"${bosh_deployment}[-0-9a-f]*\"})",
          "interval": "",
          "intervalFactor": 2,
          "legendFormat": "Latency",
          "metric": "firehose_value_metric_bbs_request_latency",
          "refId": "A",
          "step": 10
        }
      ],
      "thresholds": [],
      "timeFrom": null,
      "timeRegions": [],
      "timeShift": null,
      "title": "BBS Request Latency (max)",
      "tooltip": {
        "shared": true,
        "sort": 0,
        "value_type": "individual"
      },
      "transparent": true,
      "type": "graph",
      "xaxis": {
        "buckets": null,
        "mode": "time",
        "name": null,
        "show": true,
        "values": []
      },
      "yaxes": [
        {
          "$$hashKey": "object:1064",
          "format": "ns",
          "label": "",
          "logBase": 1,
          "max": null,
          "min": "0",
          "show": true
        },
        {
          "$$hashKey": "object:1065",
          "format": "short",
          "label": null,
          "logBase": 1,
          "max": null,
          "min": null,
          "show": false
        }
      ],
      "yaxis": {
        "align": false,
        "alignLevel": null
      }
    },
    {
      "aliasColors": {},
      "bars": false,
      "dashLength": 10,
      "dashes": false,
      "datasource": "${DS_PROMETHEUS}",
      "description": "Max time in nanoseconds that the BBS took to run its LRP and Task convergence pass. Emitted when LRP and Task convergence runs.",
      "fieldConfig": {
        "defaults": {
          "custom": {}
        },
        "overrides": []
      },
      "fill": 1,
      "fillGradient": 0,
      "gridPos": {
        "h": 5,
        "w": 8,
        "x": 16,
        "y": 9
      },
      "hiddenSeries": false,
      "id": 4,
      "legend": {
        "avg": false,
        "current": false,
        "max": false,
        "min": false,
        "show": true,
        "total": false,
        "values": false
      },
      "lines": true,
      "linewidth": 1,
      "links": [],
      "nullPointMode": "null",
      "options": {
        "alertThreshold": true
      },
      "percentage": false,
      "pluginVersion": "7.3.3",
      "pointradius": 5,
      "points": false,
      "renderer": "flot",
      "seriesOverrides": [],
      "spaceLength": 10,
      "stack": false,
      "steppedLine": false,
      "targets": [
        {
          "expr": "max(firehose_value_metric_bbs_convergence_lrp_duration{environment=~\"$environment\",bosh_deployment=~\"${bosh_deployment}[-0-9a-f]*\"})",
          "hide": false,
          "interval": "",
          "intervalFactor": 2,
          "legendFormat": "LRPs",
          "metric": "firehose_value_metric_bbs_convergence_lrp_duration",
          "refId": "A",
          "step": 10
        },
        {
          "expr": "max(firehose_value_metric_bbs_convergence_task_duration{environment=~\"$environment\",bosh_deployment=~\"${bosh_deployment}[-0-9a-f]*\"})",
          "interval": "",
          "intervalFactor": 2,
          "legendFormat": "Tasks",
          "refId": "B",
          "step": 10
        }
      ],
      "thresholds": [],
      "timeFrom": null,
      "timeRegions": [],
      "timeShift": null,
      "title": "BBS Convergence Duration (max)",
      "tooltip": {
        "shared": true,
        "sort": 0,
        "value_type": "individual"
      },
      "transparent": true,
      "type": "graph",
      "xaxis": {
        "buckets": null,
        "mode": "time",
        "name": null,
        "show": true,
        "values": []
      },
      "yaxes": [
        {
          "$$hashKey": "object:1145",
          "format": "ns",
          "label": "",
          "logBase": 1,
          "max": null,
          "min": "0",
          "show": true
        },
        {
          "$$hashKey": "object:1146",
          "format": "short",
          "label": null,
          "logBase": 1,
          "max": null,
          "min": null,
          "show": false
        }
      ],
      "yaxis": {
        "align": false,
        "alignLevel": null
      }
    },
    {
      "aliasColors": {},
      "bars": false,
      "dashLength": 10,
      "dashes": false,
      "datasource": "${DS_PROMETHEUS}",
      "description": "Max number of requests per second received by the Gorouter.",
      "fieldConfig": {
        "defaults": {
          "custom": {}
        },
        "overrides": []
      },
      "fill": 1,
      "fillGradient": 0,
      "gridPos": {
        "h": 5,
        "w": 8,
        "x": 0,
        "y": 14
      },
      "hiddenSeries": false,
      "id": 17,
      "legend": {
        "avg": false,
        "current": false,
        "max": false,
        "min": false,
        "show": true,
        "total": false,
        "values": false
      },
      "lines": true,
      "linewidth": 1,
      "links": [],
      "nullPointMode": "null",
      "options": {
        "alertThreshold": true
      },
      "percentage": false,
      "pluginVersion": "7.3.3",
      "pointradius": 5,
      "points": false,
      "renderer": "flot",
      "seriesOverrides": [],
      "spaceLength": 10,
      "stack": false,
      "steppedLine": false,
      "targets": [
        {
          "expr": "max(rate(firehose_counter_event_gorouter_total_requests_total{environment=~\"$environment\",bosh_deployment=~\"${bosh_deployment}[-0-9a-f]*\"}[5m]))",
          "interval": "5m",
          "intervalFactor": 2,
          "legendFormat": "Req/Sec",
          "metric": "",
          "refId": "A",
          "step": 600
        }
      ],
      "thresholds": [],
      "timeFrom": null,
      "timeRegions": [],
      "timeShift": null,
      "title": "Router Requests per Second (max)",
      "tooltip": {
        "shared": true,
        "sort": 0,
        "value_type": "individual"
      },
      "transparent": true,
      "type": "graph",
      "xaxis": {
        "buckets": null,
        "mode": "time",
        "name": null,
        "show": true,
        "values": []
      },
      "yaxes": [
        {
          "$$hashKey": "object:1226",
          "format": "short",
          "label": null,
          "logBase": 1,
          "max": null,
          "min": "0",
          "show": true
        },
        {
          "$$hashKey": "object:1227",
          "format": "short",
          "label": null,
          "logBase": 1,
          "max": null,
          "min": null,
          "show": false
        }
      ],
      "yaxis": {
        "align": false,
        "alignLevel": null
      }
    },
    {
      "aliasColors": {},
      "bars": false,
      "dashLength": 10,
      "dashes": false,
      "datasource": "${DS_PROMETHEUS}",
      "description": "Max time in nanoseconds that the Gorouter took to handle requests to its application endpoints.",
      "fieldConfig": {
        "defaults": {
          "custom": {}
        },
        "overrides": []
      },
      "fill": 1,
      "fillGradient": 0,
      "gridPos": {
        "h": 5,
        "w": 8,
        "x": 8,
        "y": 14
      },
      "hiddenSeries": false,
      "id": 21,
      "legend": {
        "avg": false,
        "current": false,
        "max": false,
        "min": false,
        "show": true,
        "total": false,
        "values": false
      },
      "lines": true,
      "linewidth": 1,
      "links": [],
      "nullPointMode": "null",
      "options": {
        "alertThreshold": true
      },
      "percentage": false,
      "pluginVersion": "7.3.3",
      "pointradius": 5,
      "points": false,
      "renderer": "flot",
      "seriesOverrides": [],
      "spaceLength": 10,
      "stack": false,
      "steppedLine": false,
      "targets": [
        {
          "expr": "max(firehose_value_metric_gorouter_latency{environment=~\"$environment\",bosh_deployment=~\"${bosh_deployment}[-0-9a-f]*\"})",
          "interval": "5m",
          "intervalFactor": 2,
          "legendFormat": "Latency",
          "metric": "",
          "refId": "A",
          "step": 600
        }
      ],
      "thresholds": [],
      "timeFrom": null,
      "timeRegions": [],
      "timeShift": null,
      "title": "Router Latency (max)",
      "tooltip": {
        "shared": true,
        "sort": 0,
        "value_type": "individual"
      },
      "transparent": true,
      "type": "graph",
      "xaxis": {
        "buckets": null,
        "mode": "time",
        "name": null,
        "show": true,
        "values": []
      },
      "yaxes": [
        {
          "$$hashKey": "object:1307",
          "format": "ns",
          "label": null,
          "logBase": 1,
          "max": null,
          "min": "0",
          "show": true
        },
        {
          "$$hashKey": "object:1308",
          "format": "short",
          "label": null,
          "logBase": 1,
          "max": null,
          "min": null,
          "show": false
        }
      ],
      "yaxis": {
        "align": false,
        "alignLevel": null
      }
    },
    {
      "aliasColors": {},
      "bars": false,
      "dashLength": 10,
      "dashes": false,
      "datasource": "${DS_PROMETHEUS}",
      "description": "Max number of Gorouter's HTTP Bad Gateway responses per second.",
      "fieldConfig": {
        "defaults": {
          "custom": {}
        },
        "overrides": []
      },
      "fill": 1,
      "fillGradient": 0,
      "gridPos": {
        "h": 5,
        "w": 8,
        "x": 16,
        "y": 14
      },
      "hiddenSeries": false,
      "id": 13,
      "legend": {
        "avg": false,
        "current": false,
        "max": false,
        "min": false,
        "show": false,
        "total": false,
        "values": false
      },
      "lines": true,
      "linewidth": 1,
      "links": [],
      "nullPointMode": "null",
      "options": {
        "alertThreshold": true
      },
      "percentage": false,
      "pluginVersion": "7.3.3",
      "pointradius": 5,
      "points": false,
      "renderer": "flot",
      "seriesOverrides": [],
      "spaceLength": 10,
      "stack": false,
      "steppedLine": false,
      "targets": [
        {
          "expr": "max(rate(firehose_counter_event_gorouter_bad_gateways_total{environment=~\"$environment\",bosh_deployment=~\"${bosh_deployment}[-0-9a-f]*\"}[5m]))",
          "interval": "",
          "intervalFactor": 2,
          "legendFormat": "Resp/sec",
          "metric": "firehose_counter_event_gorouter_responses_5_xx_tota",
          "refId": "A",
          "step": 10
        }
      ],
      "thresholds": [],
      "timeFrom": null,
      "timeRegions": [],
      "timeShift": null,
      "title": "Router Bad Gateway Responses per Second (max)",
      "tooltip": {
        "shared": true,
        "sort": 0,
        "value_type": "individual"
      },
      "transparent": true,
      "type": "graph",
      "xaxis": {
        "buckets": null,
        "mode": "time",
        "name": null,
        "show": true,
        "values": []
      },
      "yaxes": [
        {
          "$$hashKey": "object:410",
          "format": "none",
          "label": null,
          "logBase": 1,
          "max": null,
          "min": "0",
          "show": true
        },
        {
          "$$hashKey": "object:411",
          "format": "short",
          "label": null,
          "logBase": 1,
          "max": null,
          "min": null,
          "show": false
        }
      ],
      "yaxis": {
        "align": false,
        "alignLevel": null
      }
    },
    {
      "aliasColors": {},
      "bars": false,
      "dashLength": 10,
      "dashes": false,
      "datasource": "${DS_PROMETHEUS}",
      "description": "Max number of requests per second received by the Cloud Controller.",
      "fieldConfig": {
        "defaults": {
          "custom": {}
        },
        "overrides": []
      },
      "fill": 1,
      "fillGradient": 0,
      "gridPos": {
        "h": 5,
        "w": 8,
        "x": 0,
        "y": 19
      },
      "hiddenSeries": false,
      "id": 30,
      "legend": {
        "avg": false,
        "current": false,
        "max": false,
        "min": false,
        "show": true,
        "total": false,
        "values": false
      },
      "lines": true,
      "linewidth": 1,
      "links": [],
      "nullPointMode": "null",
      "options": {
        "alertThreshold": true
      },
      "percentage": false,
      "pluginVersion": "7.3.3",
      "pointradius": 5,
      "points": false,
      "renderer": "flot",
      "seriesOverrides": [],
      "spaceLength": 10,
      "stack": false,
      "steppedLine": false,
      "targets": [
        {
          "expr": "max(rate(firehose_value_metric_cc_requests_completed{environment=~\"$environment\",bosh_deployment=~\"${bosh_deployment}[-0-9a-f]*\"}[5m]))",
          "interval": "",
          "intervalFactor": 2,
          "legendFormat": "Req/sec",
          "refId": "A",
          "step": 10
        }
      ],
      "thresholds": [],
      "timeFrom": null,
      "timeRegions": [],
      "timeShift": null,
      "title": "CC Requests Completed per Second (max)",
      "tooltip": {
        "shared": true,
        "sort": 0,
        "value_type": "individual"
      },
      "transparent": true,
      "type": "graph",
      "xaxis": {
        "buckets": null,
        "mode": "time",
        "name": null,
        "show": true,
        "values": []
      },
      "yaxes": [
        {
          "$$hashKey": "object:260",
          "format": "short",
          "label": null,
          "logBase": 1,
          "max": null,
          "min": null,
          "show": true
        },
        {
          "$$hashKey": "object:261",
          "format": "short",
          "label": null,
          "logBase": 1,
          "max": null,
          "min": null,
          "show": true
        }
      ],
      "yaxis": {
        "align": false,
        "alignLevel": null
      }
    },
    {
      "aliasColors": {},
      "bars": false,
      "dashLength": 10,
      "dashes": false,
      "datasource": "${DS_PROMETHEUS}",
      "fieldConfig": {
        "defaults": {
          "custom": {}
        },
        "overrides": []
      },
      "fill": 1,
      "fillGradient": 0,
      "gridPos": {
        "h": 5,
        "w": 8,
        "x": 8,
        "y": 19
      },
      "hiddenSeries": false,
      "id": 9,
      "legend": {
        "avg": false,
        "current": false,
        "max": false,
        "min": false,
        "show": true,
        "total": false,
        "values": false
      },
      "lines": true,
      "linewidth": 1,
      "links": [],
      "nullPointMode": "null",
      "options": {
        "alertThreshold": true
      },
      "percentage": false,
      "pluginVersion": "7.3.3",
      "pointradius": 5,
      "points": false,
      "renderer": "flot",
      "seriesOverrides": [],
      "spaceLength": 10,
      "stack": false,
      "steppedLine": false,
      "targets": [
        {
          "expr": "max(rate(firehose_value_metric_bbs_lr_ps_desired{environment=~\"$environment\",bosh_deployment=~\"${bosh_deployment}[-0-9a-f]*\"}[30m]))",
          "interval": "",
          "intervalFactor": 2,
          "legendFormat": "LRPs Desired",
          "metric": "firehose_value_metric_bbs_lr_ps_desired",
          "refId": "A",
          "step": 10
        },
        {
          "expr": "max(rate(firehose_value_metric_bbs_lr_ps_running{environment=~\"$environment\",bosh_deployment=~\"${bosh_deployment}[-0-9a-f]*\"}[30m]))",
          "hide": false,
          "interval": "",
          "intervalFactor": 2,
          "legendFormat": "LRPs Running",
          "metric": "",
          "refId": "B",
          "step": 10
        }
      ],
      "thresholds": [],
      "timeFrom": null,
      "timeRegions": [],
      "timeShift": null,
      "title": "LRPs Velocity (max)",
      "tooltip": {
        "shared": true,
        "sort": 0,
        "value_type": "individual"
      },
      "transparent": true,
      "type": "graph",
      "xaxis": {
        "buckets": null,
        "mode": "time",
        "name": null,
        "show": true,
        "values": []
      },
      "yaxes": [
        {
          "$$hashKey": "object:1629",
          "format": "short",
          "label": "",
          "logBase": 1,
          "max": null,
          "min": "0",
          "show": true
        },
        {
          "$$hashKey": "object:1630",
          "format": "short",
          "label": null,
          "logBase": 1,
          "max": null,
          "min": null,
          "show": false
        }
      ],
      "yaxis": {
        "align": false,
        "alignLevel": null
      }
    },
    {
      "aliasColors": {},
      "bars": false,
      "dashLength": 10,
      "dashes": false,
      "datasource": "${DS_PROMETHEUS}",
      "description": "Max number of GoRouter's HTTP 5xx responses per second.",
      "fieldConfig": {
        "defaults": {
          "custom": {}
        },
        "overrides": []
      },
      "fill": 1,
      "fillGradient": 0,
      "gridPos": {
        "h": 5,
        "w": 8,
        "x": 16,
        "y": 19
      },
      "hiddenSeries": false,
      "id": 31,
      "legend": {
        "avg": false,
        "current": false,
        "max": false,
        "min": false,
        "show": false,
        "total": false,
        "values": false
      },
      "lines": true,
      "linewidth": 1,
      "links": [],
      "nullPointMode": "null",
      "options": {
        "alertThreshold": true
      },
      "percentage": false,
      "pluginVersion": "7.3.3",
      "pointradius": 5,
      "points": false,
      "renderer": "flot",
      "seriesOverrides": [],
      "spaceLength": 10,
      "stack": false,
      "steppedLine": false,
      "targets": [
        {
          "expr": "max(rate(firehose_counter_event_gorouter_responses_5_xx_total{environment=~\"$environment\",bosh_deployment=~\"${bosh_deployment}[-0-9a-f]*\"}[5m]))",
          "interval": "",
          "intervalFactor": 2,
          "legendFormat": "5xx resp/sec",
          "refId": "A",
          "step": 10
        }
      ],
      "thresholds": [],
      "timeFrom": null,
      "timeRegions": [],
      "timeShift": null,
      "title": "Router 5xx Responses per Second (max)",
      "tooltip": {
        "shared": true,
        "sort": 0,
        "value_type": "individual"
      },
      "transparent": true,
      "type": "graph",
      "xaxis": {
        "buckets": null,
        "mode": "time",
        "name": null,
        "show": true,
        "values": []
      },
      "yaxes": [
        {
          "$$hashKey": "object:182",
          "format": "short",
          "label": null,
          "logBase": 1,
          "max": null,
          "min": "0",
          "show": true
        },
        {
          "$$hashKey": "object:183",
          "format": "short",
          "label": null,
          "logBase": 1,
          "max": null,
          "min": null,
          "show": true
        }
      ],
      "yaxis": {
        "align": false,
        "alignLevel": null
      }
    }
  ],
  "refresh": "30s",
  "schemaVersion": 26,
  "style": "dark",
  "tags": [
    "cf",
    "v2"
  ],
  "templating": {
    "list": [
      {
        "allValue": null,
        "current": {},
        "datasource": "${DS_PROMETHEUS}",
        "definition": "label_values(firehose_counter_event_gorouter_total_requests_total, environment)",
        "error": null,
        "hide": 0,
        "includeAll": false,
        "label": "Environment",
        "multi": false,
        "name": "environment",
        "options": [],
        "query": "label_values(firehose_counter_event_gorouter_total_requests_total, environment)",
        "refresh": 1,
        "regex": "",
        "skipUrlSync": false,
        "sort": 1,
        "tagValuesQuery": "",
        "tags": [],
        "tagsQuery": "",
        "type": "query",
        "useTags": false
      },
      {
        "allValue": null,
        "current": {},
        "datasource": "${DS_PROMETHEUS}",
        "definition": "label_values(firehose_counter_event_gorouter_total_requests_total{environment=~\"$environment\"}, bosh_deployment)",
        "error": null,
        "hide": 0,
        "includeAll": false,
        "label": "Deployment",
        "multi": false,
        "name": "bosh_deployment",
        "options": [],
        "query": "label_values(firehose_counter_event_gorouter_total_requests_total{environment=~\"$environment\"}, bosh_deployment)",
        "refresh": 1,
        "regex": "",
        "skipUrlSync": false,
        "sort": 1,
        "tagValuesQuery": "",
        "tags": [],
        "tagsQuery": "",
        "type": "query",
        "useTags": false
      }
    ]
  },
  "time": {
    "from": "now-1h",
    "to": "now"
  },
  "timepicker": {
    "refresh_intervals": [
      "5s",
      "10s",
      "30s",
      "1m",
      "5m",
      "15m",
      "30m",
      "1h",
      "2h",
      "1d"
    ],
    "time_options": [
      "5m",
      "15m",
      "1h",
      "6h",
      "12h",
      "24h",
      "2d",
      "7d",
      "30d"
    ]
  },
  "timezone": "browser",
  "title": "CF: KPIs v2",
  "uid": "cf_kpis_v2",
  "version": 2
}